LimeReport/LimeReport.so
LimeReport/__init__.py
LimeReport_qt_6_4_Z-1.7.9.dist-info/COPYING.gpl3
LimeReport_qt_6_4_Z-1.7.9.dist-info/RECORD
LimeReport_qt_6_4_Z-1.7.9.dist-info/WHEEL
LimeReport_qt_6_4_Z-1.7.9.dist-info/top_level.txt
LimeReport_qt_6_4_Z-1.7.9.dist-info/METADATA
