Metadata-Version: 2.1
Name: LimeReport-qt-6-4-Z
Version: 1.7.9
Summary: Python bindings for LimeReport
Home-page: https://github.com/python-LimeReport/python-LimeReport
Author: Maxim Slipenko
Author-email: python-limereport@maks1ms.anonaddy.com
License: GPLv3
Classifier: Environment :: X11 Applications :: Qt
Classifier: Programming Language :: C++
Classifier: Programming Language :: Python :: 3
Classifier: Programming Language :: Python :: 3.9
Classifier: License :: OSI Approved :: GNU General Public License v3 (GPLv3)
License-File: COPYING.gpl3
Requires-Dist: PySide6 ==6.4.*
Requires-Dist: shiboken6 ==6.4.*
